connections/__init__.py
connections/camera.py
connections/logger.py
connections/socket_utils.py
connections/yolo_utils.py
nammv-1.1.2.dist-info/LICENSE
nammv-1.1.2.dist-info/METADATA
nammv-1.1.2.dist-info/WHEEL
nammv-1.1.2.dist-info/top_level.txt
nammv-1.1.2.dist-info/RECORD
