Metadata-Version: 2.1
Name: nammv
Version: 1.1.2
Summary: Camera connections and socket utils
License-File: LICENSE
Requires-Dist: pypylon
Requires-Dist: ultralytics
Requires-Dist: opencv-python
Requires-Dist: numpy
Requires-Dist: termcolor
Requires-Dist: colorama
